collective.iframe-1.0.0a2-py3.11-nspkg.pth
collective/iframe/__init__.py
collective/iframe/configure.zcml
collective/iframe/interfaces.py
collective/iframe/permissions.zcml
collective/iframe/setuphandlers.py
collective/iframe/testing.py
collective/iframe/browser/__init__.py
collective/iframe/browser/configure.zcml
collective/iframe/browser/iframe.pt
collective/iframe/content/__init__.py
collective/iframe/content/iframe.py
collective/iframe/content/iframe.xml
collective/iframe/locales/README.rst
collective/iframe/locales/__init__.py
collective/iframe/locales/collective.iframe.pot
collective/iframe/locales/update.py
collective/iframe/locales/update.sh
collective/iframe/locales/en/LC_MESSAGES/collective.iframe.mo
collective/iframe/locales/en/LC_MESSAGES/collective.iframe.po
collective/iframe/profiles/default/browserlayer.xml
collective/iframe/profiles/default/catalog.xml
collective/iframe/profiles/default/metadata.xml
collective/iframe/profiles/default/rolemap.xml
collective/iframe/profiles/default/types.xml
collective/iframe/profiles/default/registry/icons.xml
collective/iframe/profiles/default/registry/main.xml
collective/iframe/profiles/default/types/Iframe.xml
collective/iframe/profiles/uninstall/browserlayer.xml
collective/iframe/tests/__init__.py
collective/iframe/tests/test_ct_iframe.py
collective/iframe/tests/test_setup.py
collective.iframe-1.0.0a2.dist-info/LICENSE.GPL
collective.iframe-1.0.0a2.dist-info/LICENSE.rst
collective.iframe-1.0.0a2.dist-info/METADATA
collective.iframe-1.0.0a2.dist-info/WHEEL
collective.iframe-1.0.0a2.dist-info/entry_points.txt
collective.iframe-1.0.0a2.dist-info/namespace_packages.txt
collective.iframe-1.0.0a2.dist-info/top_level.txt
collective.iframe-1.0.0a2.dist-info/RECORD
